csv2gs/__init__.py
csv2gs-0.1.0.dist-info/WHEEL
csv2gs-0.1.0.dist-info/METADATA
csv2gs-0.1.0.dist-info/RECORD
