Metadata-Version: 2.1
Name: csv2gs
Version: 0.1.0
Summary: Upload CSV to Google Sheets using CLI
Author: Alexey Kulichevskiy
Author-email: alex@alexchevsky.com
Requires-Python: >=3.9,<4.0
Classifier: Programming Language :: Python :: 3
Classifier: Programming Language :: Python :: 3.9
